vinculum/VERSION
vinculum/__init__.py
vinculum/log.py
vinculum/math.py
vinculum/py.typed
vinculum/rational.py
vinculum-1.0.0b12.dist-info/LICENSE
vinculum-1.0.0b12.dist-info/METADATA
vinculum-1.0.0b12.dist-info/WHEEL
vinculum-1.0.0b12.dist-info/top_level.txt
vinculum-1.0.0b12.dist-info/RECORD
