Metadata-Version: 2.1
Name: vinculum
Version: 1.0.0b12
Summary: Large numbers with high precision
Home-page: https://github.com/cariad/vinculum
Author: Cariad Eccleston
Author-email: cariad@cariad.earth
License: MIT
Project-URL: Documentation, https://cariad.github.io/vinculum/
Project-URL: Funding, https://github.com/sponsors/cariad
Project-URL: Issues, https://github.com/cariad/vinculum/issues
Project-URL: Source, https://github.com/cariad/vinculum
Classifier: Development Status :: 4 - Beta
Classifier: License :: OSI Approved :: MIT License
Classifier: Natural Language :: English
Classifier: Operating System :: OS Independent
Classifier: Programming Language :: Python :: 3.11
Classifier: Typing :: Typed
Requires-Python: >=3.11
License-File: LICENSE
